{
    "login": "ry",
    "id": 80,
    "node_id": "MDQ6VXNlcjgw",
    "avatar_url": "https://avatars1.githubusercontent.com/u/80?v=4",
    "gravatar_id": "",
    "url": "https://api.github.com/users/ry",
    "html_url": "https://github.com/ry",
    "followers_url": "https://api.github.com/users/ry/followers",
    "following_url": "https://api.github.com/users/ry/following{/other_user}",
    "gists_url": "https://api.github.com/users/ry/gists{/gist_id}",
    "starred_url": "https://api.github.com/users/ry/starred{/owner}{/repo}",
    "subscriptions_url": "https://api.github.com/users/ry/subscriptions",
    "organizations_url": "https://api.github.com/users/ry/orgs",
    "repos_url": "https://api.github.com/users/ry/repos",
    "events_url": "https://api.github.com/users/ry/events{/privacy}",
    "received_events_url": "https://api.github.com/users/ry/received_events",
    "type": "User",
    "site_admin": false,
    "name": "Ryan Dahl",
    "company": null,
    "blog": "http://tinyclouds.org/",
    "location": null,
    "email": null,
    "hireable": null,
    "bio": null,
    "public_repos": 20,
    "public_gists": 300,
    "followers": 14375,
    "following": 32,
    "created_at": "2008-01-29T08:50:34Z",
    "updated_at": "2018-09-20T06:12:40Z"
}
